pollination/three_phase/__init__.py
pollination/three_phase/entry.py
pollination/three_phase/three_phase/__init__.py
pollination/three_phase/three_phase/_daylight_matrix.py
pollination/three_phase/three_phase/_multiply_matrix.py
pollination/three_phase/three_phase/_view_matrix.py
pollination/three_phase/three_phase/calculation.py
pollination/three_phase/three_phase/preparation.py
pollination/three_phase/two_phase/dynamic/_raytracing.py
pollination/three_phase/two_phase/dynamic/entry.py
pollination_three_phase-0.2.11.dist-info/LICENSE
pollination_three_phase-0.2.11.dist-info/METADATA
pollination_three_phase-0.2.11.dist-info/WHEEL
pollination_three_phase-0.2.11.dist-info/top_level.txt
pollination_three_phase-0.2.11.dist-info/RECORD
