Metadata-Version: 2.1
Name: pollination-three-phase
Version: 0.2.11
Summary: Three phase recipe for Pollination.
Home-page: https://github.com/pollination/three-phase
Author: ladybug-tools
Author-email: info@ladybug.tools
Maintainer: ladybug-tools
Maintainer-email: info@ladybug.tools
License: PolyForm Shield License 1.0.0, https://polyformproject.org/wp-content/uploads/2020/06/PolyForm-Shield-1.0.0.txt
Project-URL: icon, https://raw.githubusercontent.com/ladybug-tools/artwork/master/icons_components/honeybee/png/3phaserecipe.png
Project-URL: docker, https://hub.docker.com/r/ladybugtools/honeybee-radiance
Keywords: honeybee,radiance,ladybug-tools,daylight,three-phase
License-File: LICENSE
Requires-Dist: pollination-honeybee-radiance (>=0.22.35)
Requires-Dist: pollination-honeybee-radiance-postprocess (>=0.0.35)
Requires-Dist: pollination-path (>=0.3.2)
Requires-Dist: pollination-alias (>=0.11.6)
